pyhooks/__init__.py
pyhooks/hooks.py
pyhooks/tags.py
pyhooks/utils.py
tests/__init__.py
tests/conftest.py
tests/hooks.py
tests/tags.py
tests/utils.py
pyhooks-1.0.3.dist-info/METADATA
pyhooks-1.0.3.dist-info/WHEEL
pyhooks-1.0.3.dist-info/top_level.txt
pyhooks-1.0.3.dist-info/RECORD
