Metadata-Version: 2.1
Name: pyhooks
Version: 1.0.3
Summary: Python hooks for methods
Home-page: https://github.com/Shir0kamii/pyhooks
Author: Shir0kamii
Author-email: shir0kamii@gmail.com
License: UNKNOWN
Download-URL: https://github.com/Shir0kamii/pyhooks/tags
Platform: any
Classifier: Development Status :: 5 - Production/Stable
Classifier: Operating System :: Microsoft :: Windows
Classifier: Operating System :: POSIX :: Linux
Classifier: Programming Language :: Python
Classifier: Programming Language :: Python :: 2.7
Classifier: Programming Language :: Python :: 3
Classifier: Programming Language :: Python :: 3.2
Classifier: Programming Language :: Python :: 3.3
Classifier: Programming Language :: Python :: 3.4
Classifier: Programming Language :: Python :: 3.5
Classifier: Programming Language :: Python :: 3.6
Classifier: Programming Language :: Python :: 3.7
Classifier: Programming Language :: Python :: 3.8
Classifier: Topic :: Software Development :: Libraries :: Python Modules
